bolapy
